clintest/__init__.py
clintest/__main__.py
clintest/assertion.py
clintest/outcome.py
clintest/py.typed
clintest/quantifier.py
clintest/solver.py
clintest/test.py
clintest-0.4.0.dist-info/licenses/LICENSE
clintest-0.4.0.dist-info/METADATA
clintest-0.4.0.dist-info/WHEEL
clintest-0.4.0.dist-info/top_level.txt
clintest-0.4.0.dist-info/RECORD
