Metadata-Version: 2.4
Name: clintest
Version: 0.4.0
Summary: A test framework for clingo programs
Home-page: https://github.com/potassco/clintest
Author: Tobias Stolzmann
Author-email: tobias.stolzmann@uni-potsdam.de
License: MIT
License-File: LICENSE
Requires-Dist: clingo>=5.5.0
Dynamic: license-file
